simple_pytorch_wrapper/__init__.py
simple_pytorch_wrapper/examples/CNN_example_run.py
simple_pytorch_wrapper/examples/FNN_example_run.py
simple_pytorch_wrapper/examples/__init__.py
simple_pytorch_wrapper/examples/load_example_dataset.py
simple_pytorch_wrapper/examples/xNN_example_run.py
simple_pytorch_wrapper/examples/data/X.npy
simple_pytorch_wrapper/examples/data/Y.npy
simple_pytorch_wrapper/utils/NN_generators.py
simple_pytorch_wrapper/utils/__init__.py
simple_pytorch_wrapper/utils/load_data.py
simple_pytorch_wrapper/utils/network_types.py
simple_pytorch_wrapper/utils/set_seed.py
simple_pytorch_wrapper/utils/warnings.py
simple_pytorch_wrapper/wrapper/__init__.py
simple_pytorch_wrapper/wrapper/pytorch_wrapper.py
simple_pytorch_wrapper-0.0.6.dist-info/LICENSE
simple_pytorch_wrapper-0.0.6.dist-info/METADATA
simple_pytorch_wrapper-0.0.6.dist-info/WHEEL
simple_pytorch_wrapper-0.0.6.dist-info/top_level.txt
simple_pytorch_wrapper-0.0.6.dist-info/RECORD
