Metadata-Version: 2.1
Name: simple_pytorch_wrapper
Version: 0.0.6
Summary: A lightweight PyTorch wrapper for fast and easy neural network training and evaluation.
Home-page: https://github.com/burakktopal/pytorch-wrapper-package
Author: Burakktopal
Classifier: Programming Language :: Python :: 3
Classifier: License :: OSI Approved :: MIT License
Classifier: Operating System :: OS Independent
Requires-Python: >=3.7
License-File: LICENSE
Requires-Dist: torch>=2.0.0
Requires-Dist: numpy>=1.21.0
Requires-Dist: matplotlib>=3.5.0
Requires-Dist: setuptools>=42.0.0
